dazzle/__init__.py
dazzle/data.py
dazzle/evaluate.py
dazzle/logger.py
dazzle/models.py
dazzle/runner.py
dazzle/.ipynb_checkpoints/__init__-checkpoint.py
dazzle/.ipynb_checkpoints/data-checkpoint.py
dazzle/.ipynb_checkpoints/evaluate-checkpoint.py
dazzle/.ipynb_checkpoints/logger-checkpoint.py
dazzle/.ipynb_checkpoints/models-checkpoint.py
dazzle/.ipynb_checkpoints/runner-checkpoint.py
grn_dazzle-0.0.2.dist-info/LICENSE
grn_dazzle-0.0.2.dist-info/WHEEL
grn_dazzle-0.0.2.dist-info/METADATA
grn_dazzle-0.0.2.dist-info/RECORD
